hello_teaxyzzz8
